AUTHORS.rst
CONTRIBUTING.rst
HISTORY.rst
LICENSE
MANIFEST.in
README.rst
setup.cfg
setup.py
Python_Card_Game.egg-info/PKG-INFO
Python_Card_Game.egg-info/SOURCES.txt
Python_Card_Game.egg-info/dependency_links.txt
Python_Card_Game.egg-info/not-zip-safe
Python_Card_Game.egg-info/top_level.txt
docs/Makefile
docs/authors.rst
docs/conf.py
docs/contributing.rst
docs/history.rst
docs/index.rst
docs/installation.rst
docs/make.bat
docs/modules.rst
docs/python_card_game.engine.rst
docs/python_card_game.rst
docs/readme.rst
docs/todo.rst
docs/usage.rst
python_card_game/__init__.py
python_card_game/python_card_game.py
tests/__init__.py
tests/test_card.py
tests/test_python_card_game.py