Metadata-Version: 1.1
Name: Python-Card-Game
Version: 0.1.0
Summary: A simple python module that implements a few classes need to construct a card game
Home-page: https://github.com/cosgroma/Python-Card-Game
Author: Mathew Cosgrove
Author-email: cosgroma@gmail.com
License: ISCL
Keywords: python_card_game
Platform: UNKNOWN
Classifier: Development Status :: 2 - Pre-Alpha
Classifier: Intended Audience :: Developers
Classifier: License :: OSI Approved :: ISC License (ISCL)
Classifier: Natural Language :: English
Classifier: Programming Language :: Python :: 2
Classifier: Programming Language :: Python :: 2.6
Classifier: Programming Language :: Python :: 2.7
Classifier: Programming Language :: Python :: 3
Classifier: Programming Language :: Python :: 3.3
Classifier: Programming Language :: Python :: 3.4
Classifier: Programming Language :: Python :: 3.5
